redantic/__init__.py
redantic/storage.py
redantic-0.1.1.dist-info/LICENSE
redantic-0.1.1.dist-info/WHEEL
redantic-0.1.1.dist-info/METADATA
redantic-0.1.1.dist-info/RECORD
