Metadata-Version: 2.1
Name: redantic
Version: 0.1.1
Summary: Simple redis storage for pydantic objects with an interface of the MutableMapping.
Author: apollon
Author-email: Apollon76@yandex.ru
Requires-Python: >=3.10,<4.0
Classifier: Programming Language :: Python :: 3
Classifier: Programming Language :: Python :: 3.10
Classifier: Programming Language :: Python :: 3.11
Requires-Dist: pydantic (>=1.10.2,<2.0.0)
Requires-Dist: redis (>=4.3.4,<5.0.0)
